README.md
setup.cfg
setup.py
macrobase/__init__.py
macrobase/app.py
macrobase/cli.py
macrobase/exceptions.py
macrobase/hook.py
macrobase/logging.py
macrobase/pool.py
macrobase.egg-info/PKG-INFO
macrobase.egg-info/SOURCES.txt
macrobase.egg-info/dependency_links.txt
macrobase.egg-info/requires.txt
macrobase.egg-info/top_level.txt
tests/__init__.py
tests/conftest.py
tests/sample_app.py
tests/test_app.py