Metadata-Version: 2.1
Name: macrobase
Version: 3.0.1
Summary: Macrobase framework for build mAcroservices
Home-page: https://github.com/mbcores/macrobase
Author: Alexey Shagaleev
Author-email: alexey.shagaleev@yandex.ru
License: MIT
Platform: UNKNOWN
Provides-Extra: dev
Provides-Extra: test
